{
  "source": "Vrij op naam",
  "description": "All-in-prijs: dit is de kale inkoopprijs zoals deze op de stroombeurs geldt, plus de inkoopvergoeding, energiebelasting en ODE (1ste staffel), inclusief btw.",
  "updated_at": "2023-12-23T12:19:08.360Z",
  "currency": "EUR",
  "prices": [
    {
      "iso": "2023-12-23T00:00:00.000Z",
      "date": "2023-12-23",
      "hour": 0,
      "price": 0.18451
    },
    {
      "iso": "2023-12-23T01:00:00.000Z",
      "date": "2023-12-23",
      "hour": 1,
      "price": 0.17764
    },
    {
      "iso": "2023-12-23T02:00:00.000Z",
      "date": "2023-12-23",
      "hour": 2,
      "price": 0.17257
    },
    {
      "iso": "2023-12-23T03:00:00.000Z",
      "date": "2023-12-23",
      "hour": 3,
      "price": 0.17245
    },
    {
      "iso": "2023-12-23T04:00:00.000Z",
      "date": "2023-12-23",
      "hour": 4,
      "price": 0.17241
    },
    {
      "iso": "2023-12-23T05:00:00.000Z",
      "date": "2023-12-23",
      "hour": 5,
      "price": 0.17241
    },
    {
      "iso": "2023-12-23T06:00:00.000Z",
      "date": "2023-12-23",
      "hour": 6,
      "price": 0.17253
    },
    {
      "iso": "2023-12-23T07:00:00.000Z",
      "date": "2023-12-23",
      "hour": 7,
      "price": 0.1814
    },
    {
      "iso": "2023-12-23T08:00:00.000Z",
      "date": "2023-12-23",
      "hour": 8,
      "price": 0.19661
    },
    {
      "iso": "2023-12-23T09:00:00.000Z",
      "date": "2023-12-23",
      "hour": 9,
      "price": 0.22333
    },
    {
      "iso": "2023-12-23T10:00:00.000Z",
      "date": "2023-12-23",
      "hour": 10,
      "price": 0.2228
    },
    {
      "iso": "2023-12-23T11:00:00.000Z",
      "date": "2023-12-23",
      "hour": 11,
      "price": 0.22795
    },
    {
      "iso": "2023-12-23T12:00:00.000Z",
      "date": "2023-12-23",
      "hour": 12,
      "price": 0.22807
    },
    {
      "iso": "2023-12-23T13:00:00.000Z",
      "date": "2023-12-23",
      "hour": 13,
      "price": 0.23268
    },
    {
      "iso": "2023-12-23T14:00:00.000Z",
      "date": "2023-12-23",
      "hour": 14,
      "price": 0.23207
    },
    {
      "iso": "2023-12-23T15:00:00.000Z",
      "date": "2023-12-23",
      "hour": 15,
      "price": 0.23232
    },
    {
      "iso": "2023-12-23T16:00:00.000Z",
      "date": "2023-12-23",
      "hour": 16,
      "price": 0.23809
    },
    {
      "iso": "2023-12-23T17:00:00.000Z",
      "date": "2023-12-23",
      "hour": 17,
      "price": 0.24957
    },
    {
      "iso": "2023-12-23T18:00:00.000Z",
      "date": "2023-12-23",
      "hour": 18,
      "price": 0.25282
    },
    {
      "iso": "2023-12-23T19:00:00.000Z",
      "date": "2023-12-23",
      "hour": 19,
      "price": 0.24258
    },
    {
      "iso": "2023-12-23T20:00:00.000Z",
      "date": "2023-12-23",
      "hour": 20,
      "price": 0.23105
    },
    {
      "iso": "2023-12-23T21:00:00.000Z",
      "date": "2023-12-23",
      "hour": 21,
      "price": 0.21884
    },
    {
      "iso": "2023-12-23T22:00:00.000Z",
      "date": "2023-12-23",
      "hour": 22,
      "price": 0.197
    },
    {
      "iso": "2023-12-23T23:00:00.000Z",
      "date": "2023-12-23",
      "hour": 23,
      "price": 0.18181
    },
    {
      "iso": "2023-12-24T00:00:00.000Z",
      "date": "2023-12-24",
      "hour": 0,
      "price": 0.17229
    },
    {
      "iso": "2023-12-24T01:00:00.000Z",
      "date": "2023-12-24",
      "hour": 1,
      "price": 0.17251
    },
    {
      "iso": "2023-12-24T02:00:00.000Z",
      "date": "2023-12-24",
      "hour": 2,
      "price": 0.17211
    },
    {
      "iso": "2023-12-24T03:00:00.000Z",
      "date": "2023-12-24",
      "hour": 3,
      "price": 0.17175
    },
    {
      "iso": "2023-12-24T04:00:00.000Z",
      "date": "2023-12-24",
      "hour": 4,
      "price": 0.17091
    },
    {
      "iso": "2023-12-24T05:00:00.000Z",
      "date": "2023-12-24",
      "hour": 5,
      "price": 0.16745
    },
    {
      "iso": "2023-12-24T06:00:00.000Z",
      "date": "2023-12-24",
      "hour": 6,
      "price": 0.1664
    },
    {
      "iso": "2023-12-24T07:00:00.000Z",
      "date": "2023-12-24",
      "hour": 7,
      "price": 0.16731
    },
    {
      "iso": "2023-12-24T08:00:00.000Z",
      "date": "2023-12-24",
      "hour": 8,
      "price": 0.16889
    },
    {
      "iso": "2023-12-24T09:00:00.000Z",
      "date": "2023-12-24",
      "hour": 9,
      "price": 0.17045
    },
    {
      "iso": "2023-12-24T10:00:00.000Z",
      "date": "2023-12-24",
      "hour": 10,
      "price": 0.17241
    },
    {
      "iso": "2023-12-24T11:00:00.000Z",
      "date": "2023-12-24",
      "hour": 11,
      "price": 0.17494
    },
    {
      "iso": "2023-12-24T12:00:00.000Z",
      "date": "2023-12-24",
      "hour": 12,
      "price": 0.17249
    },
    {
      "iso": "2023-12-24T13:00:00.000Z",
      "date": "2023-12-24",
      "hour": 13,
      "price": 0.17247
    },
    {
      "iso": "2023-12-24T14:00:00.000Z",
      "date": "2023-12-24",
      "hour": 14,
      "price": 0.17249
    },
    {
      "iso": "2023-12-24T15:00:00.000Z",
      "date": "2023-12-24",
      "hour": 15,
      "price": 0.17245
    },
    {
      "iso": "2023-12-24T16:00:00.000Z",
      "date": "2023-12-24",
      "hour": 16,
      "price": 0.17257
    },
    {
      "iso": "2023-12-24T17:00:00.000Z",
      "date": "2023-12-24",
      "hour": 17,
      "price": 0.17362
    },
    {
      "iso": "2023-12-24T18:00:00.000Z",
      "date": "2023-12-24",
      "hour": 18,
      "price": 0.1948
    },
    {
      "iso": "2023-12-24T19:00:00.000Z",
      "date": "2023-12-24",
      "hour": 19,
      "price": 0.21018
    },
    {
      "iso": "2023-12-24T20:00:00.000Z",
      "date": "2023-12-24",
      "hour": 20,
      "price": 0.21452
    },
    {
      "iso": "2023-12-24T21:00:00.000Z",
      "date": "2023-12-24",
      "hour": 21,
      "price": 0.18451
    },
    {
      "iso": "2023-12-24T22:00:00.000Z",
      "date": "2023-12-24",
      "hour": 22,
      "price": 0.17485
    },
    {
      "iso": "2023-12-24T23:00:00.000Z",
      "date": "2023-12-24",
      "hour": 23,
      "price": 0.17241
    }
  ]
}
