{
  "source": "Vrij op naam",
  "description": "All-in-prijs: dit is de kale inkoopprijs zoals deze op de stroombeurs geldt, plus de inkoopvergoeding, energiebelasting en ODE (1ste staffel), inclusief btw.",
  "updated_at": "2026-01-06T12:34:02.872Z",
  "currency": "EUR",
  "prices": [
    {
      "iso": "2026-01-06T00:00:00.000Z",
      "date": "2026-01-06",
      "hour": 0,
      "price": 0.25749
    },
    {
      "iso": "2026-01-06T01:00:00.000Z",
      "date": "2026-01-06",
      "hour": 1,
      "price": 0.25738
    },
    {
      "iso": "2026-01-06T02:00:00.000Z",
      "date": "2026-01-06",
      "hour": 2,
      "price": 0.25369
    },
    {
      "iso": "2026-01-06T03:00:00.000Z",
      "date": "2026-01-06",
      "hour": 3,
      "price": 0.25192
    },
    {
      "iso": "2026-01-06T04:00:00.000Z",
      "date": "2026-01-06",
      "hour": 4,
      "price": 0.25478
    },
    {
      "iso": "2026-01-06T05:00:00.000Z",
      "date": "2026-01-06",
      "hour": 5,
      "price": 0.26028
    },
    {
      "iso": "2026-01-06T06:00:00.000Z",
      "date": "2026-01-06",
      "hour": 6,
      "price": 0.27757
    },
    {
      "iso": "2026-01-06T07:00:00.000Z",
      "date": "2026-01-06",
      "hour": 7,
      "price": 0.2984
    },
    {
      "iso": "2026-01-06T08:00:00.000Z",
      "date": "2026-01-06",
      "hour": 8,
      "price": 0.32948
    },
    {
      "iso": "2026-01-06T09:00:00.000Z",
      "date": "2026-01-06",
      "hour": 9,
      "price": 0.33509
    },
    {
      "iso": "2026-01-06T10:00:00.000Z",
      "date": "2026-01-06",
      "hour": 10,
      "price": 0.31817
    },
    {
      "iso": "2026-01-06T11:00:00.000Z",
      "date": "2026-01-06",
      "hour": 11,
      "price": 0.30901
    },
    {
      "iso": "2026-01-06T12:00:00.000Z",
      "date": "2026-01-06",
      "hour": 12,
      "price": 0.29276
    },
    {
      "iso": "2026-01-06T13:00:00.000Z",
      "date": "2026-01-06",
      "hour": 13,
      "price": 0.28293
    },
    {
      "iso": "2026-01-06T14:00:00.000Z",
      "date": "2026-01-06",
      "hour": 14,
      "price": 0.28245
    },
    {
      "iso": "2026-01-06T15:00:00.000Z",
      "date": "2026-01-06",
      "hour": 15,
      "price": 0.29271
    },
    {
      "iso": "2026-01-06T16:00:00.000Z",
      "date": "2026-01-06",
      "hour": 16,
      "price": 0.30623
    },
    {
      "iso": "2026-01-06T17:00:00.000Z",
      "date": "2026-01-06",
      "hour": 17,
      "price": 0.31593
    },
    {
      "iso": "2026-01-06T18:00:00.000Z",
      "date": "2026-01-06",
      "hour": 18,
      "price": 0.31022
    },
    {
      "iso": "2026-01-06T19:00:00.000Z",
      "date": "2026-01-06",
      "hour": 19,
      "price": 0.29915
    },
    {
      "iso": "2026-01-06T20:00:00.000Z",
      "date": "2026-01-06",
      "hour": 20,
      "price": 0.27795
    },
    {
      "iso": "2026-01-06T21:00:00.000Z",
      "date": "2026-01-06",
      "hour": 21,
      "price": 0.23585
    },
    {
      "iso": "2026-01-06T22:00:00.000Z",
      "date": "2026-01-06",
      "hour": 22,
      "price": 0.23631
    },
    {
      "iso": "2026-01-06T23:00:00.000Z",
      "date": "2026-01-06",
      "hour": 23,
      "price": 0.22433
    },
    {
      "iso": "2026-01-07T00:00:00.000Z",
      "date": "2026-01-07",
      "hour": 0,
      "price": 0.23648
    },
    {
      "iso": "2026-01-07T01:00:00.000Z",
      "date": "2026-01-07",
      "hour": 1,
      "price": 0.2375
    },
    {
      "iso": "2026-01-07T02:00:00.000Z",
      "date": "2026-01-07",
      "hour": 2,
      "price": 0.23099
    },
    {
      "iso": "2026-01-07T03:00:00.000Z",
      "date": "2026-01-07",
      "hour": 3,
      "price": 0.22712
    },
    {
      "iso": "2026-01-07T04:00:00.000Z",
      "date": "2026-01-07",
      "hour": 4,
      "price": 0.22643
    },
    {
      "iso": "2026-01-07T05:00:00.000Z",
      "date": "2026-01-07",
      "hour": 5,
      "price": 0.22475
    },
    {
      "iso": "2026-01-07T06:00:00.000Z",
      "date": "2026-01-07",
      "hour": 6,
      "price": 0.22589
    },
    {
      "iso": "2026-01-07T07:00:00.000Z",
      "date": "2026-01-07",
      "hour": 7,
      "price": 0.23916
    },
    {
      "iso": "2026-01-07T08:00:00.000Z",
      "date": "2026-01-07",
      "hour": 8,
      "price": 0.24511
    },
    {
      "iso": "2026-01-07T09:00:00.000Z",
      "date": "2026-01-07",
      "hour": 9,
      "price": 0.25758
    },
    {
      "iso": "2026-01-07T10:00:00.000Z",
      "date": "2026-01-07",
      "hour": 10,
      "price": 0.2654
    },
    {
      "iso": "2026-01-07T11:00:00.000Z",
      "date": "2026-01-07",
      "hour": 11,
      "price": 0.26113
    },
    {
      "iso": "2026-01-07T12:00:00.000Z",
      "date": "2026-01-07",
      "hour": 12,
      "price": 0.25081
    },
    {
      "iso": "2026-01-07T13:00:00.000Z",
      "date": "2026-01-07",
      "hour": 13,
      "price": 0.24622
    },
    {
      "iso": "2026-01-07T14:00:00.000Z",
      "date": "2026-01-07",
      "hour": 14,
      "price": 0.24164
    },
    {
      "iso": "2026-01-07T15:00:00.000Z",
      "date": "2026-01-07",
      "hour": 15,
      "price": 0.24459
    },
    {
      "iso": "2026-01-07T16:00:00.000Z",
      "date": "2026-01-07",
      "hour": 16,
      "price": 0.2523
    },
    {
      "iso": "2026-01-07T17:00:00.000Z",
      "date": "2026-01-07",
      "hour": 17,
      "price": 0.26601
    },
    {
      "iso": "2026-01-07T18:00:00.000Z",
      "date": "2026-01-07",
      "hour": 18,
      "price": 0.28117
    },
    {
      "iso": "2026-01-07T19:00:00.000Z",
      "date": "2026-01-07",
      "hour": 19,
      "price": 0.26567
    },
    {
      "iso": "2026-01-07T20:00:00.000Z",
      "date": "2026-01-07",
      "hour": 20,
      "price": 0.248
    },
    {
      "iso": "2026-01-07T21:00:00.000Z",
      "date": "2026-01-07",
      "hour": 21,
      "price": 0.24046
    },
    {
      "iso": "2026-01-07T22:00:00.000Z",
      "date": "2026-01-07",
      "hour": 22,
      "price": 0.24304
    },
    {
      "iso": "2026-01-07T23:00:00.000Z",
      "date": "2026-01-07",
      "hour": 23,
      "price": 0.2409
    }
  ]
}
